transact/__init__.py
transact/test_transact.py
transact/transact.py
transact/transact_config.py
transact/version.py
transact_tf-0.1.1.dist-info/LICENSE
transact_tf-0.1.1.dist-info/METADATA
transact_tf-0.1.1.dist-info/WHEEL
transact_tf-0.1.1.dist-info/top_level.txt
transact_tf-0.1.1.dist-info/RECORD
